versao_final/decodificador.v
module decodificador(
  input wire [3:0] min, sec_tens, sec_ones, 
  output reg [6:0] min_segs, sec_tens_segs, sec_ones_segs);

  always@(min)
    case(min)
      4'b0000 : min_segs = 7'b100_0000;
      4'b0001 : min_segs = 7'b111_1001;
      4'b0010 : min_segs = 7'b010_0100;
      4'b0011 : min_segs = 7'b011_0000;
      4'b0100 : min_segs = 7'b001_1001;
      4'b0101 : min_segs = 7'b001_0010;
      4'b0110 : min_segs = 7'b000_0010;
      4'b0111 : min_segs = 7'b111_1000;
      4'b1000 : min_segs = 7'b000_0000;
      4'b1001 : min_segs = 7'b001_0000;
    endcase
  
  always@(sec_tens)
    case(sec_tens)
      4'b0000 : sec_tens_segs = 7'b100_0000;
      4'b0001 : sec_tens_segs = 7'b111_1001;
      4'b0010 : sec_tens_segs = 7'b010_0100;
      4'b0011 : sec_tens_segs = 7'b011_0000;
      4'b0100 : sec_tens_segs= 7'b001_1001;
      4'b0101 : sec_tens_segs = 7'b001_0010;
      4'b0110 : sec_tens_segs = 7'b000_0010;
      4'b0111 : sec_tens_segs = 7'b111_1000;
      4'b1000 : sec_tens_segs = 7'b000_0000;
      4'b1001 : sec_tens_segs = 7'b001_0000;
    endcase
  
  always@(sec_ones)
    case(sec_ones)
      4'b0000 : sec_ones_segs = 7'b100_0000;
      4'b0001 : sec_ones_segs = 7'b111_1001;
      4'b0010 : sec_ones_segs = 7'b010_0100;
      4'b0011 : sec_ones_segs = 7'b011_0000;
      4'b0100 : sec_ones_segs= 7'b001_1001;
      4'b0101 : sec_ones_segs = 7'b001_0010;
      4'b0110 : sec_ones_segs = 7'b000_0010;
      4'b0111 : sec_ones_segs = 7'b111_1000;
      4'b1000 : sec_ones_segs = 7'b000_0000;
      4'b1001 : sec_ones_segs = 7'b001_0000;
    endcase

endmodule

microwave-main/Nivel1/Nivel2/decodificador/decodificador_tb.v
`timescale 1ns/1ns
`include "decodificador.v"

module decodificador_tb;

    reg [3:0] min_tb, sec_tens_tb, sec_ones_tb;
  	wire [6:0] min_segs_tb, sec_tens_segs_tb, sec_ones_segs_tb;

  	decodificador uut(.min(min_tb), .sec_tens(sec_tens_tb), .sec_ones(sec_ones_tb), .min_segs(min_segs_tb), .sec_tens_segs(sec_tens_segs_tb), .sec_ones_segs(sec_ones_segs_tb));

    initial
        begin

            $dumpfile("decodificador_tb.vcd");
            $dumpvars(0, decodificador_tb);

                min_tb=4'b0000; sec_tens_tb=4'b0000; sec_ones_tb=4'b0000;  
            #5  min_tb=4'b0001; sec_tens_tb=4'b0001; sec_ones_tb=4'b0001; 
         	  #5  min_tb=4'b0010; sec_tens_tb=4'b0010; sec_ones_tb=4'b0010;
            #5  min_tb=4'b0011; sec_tens_tb=4'b0011; sec_ones_tb=4'b0011;
            #5  min_tb=4'b0100; sec_tens_tb=4'b0100; sec_ones_tb=4'b0100;
            #5  min_tb=4'b0101; sec_tens_tb=4'b0101; sec_ones_tb=4'b0101;
          	#5  min_tb=4'b0110; sec_tens_tb=4'b0110; sec_ones_tb=4'b0110;
            #5  min_tb=4'b0111; sec_tens_tb=4'b0111; sec_ones_tb=4'b0111;
          	#5  min_tb=4'b1000; sec_tens_tb=4'b1000; sec_ones_tb=4'b1000;
            #5  min_tb=4'b1001; sec_tens_tb=4'b1001; sec_ones_tb=4'b1001;    
        end

endmodule

microwave-main/Nivel1/Nivel2/decodificador/decodificador_tb.vcd
$date
	Sun Apr 23 18:20:17 2023
$end
$version
	Icarus Verilog
$end
$timescale
	1ns
$end
$scope module decodificador_tb $end
$var wire 7 ! sec_tens_segs_tb [6:0] $end
$var wire 7 " sec_ones_segs_tb [6:0] $end
$var wire 7 # min_segs_tb [6:0] $end
$var reg 4 $ min_tb [3:0] $end
$var reg 4 % sec_ones_tb [3:0] $end
$var reg 4 & sec_tens_tb [3:0] $end
$scope module uut $end
$var wire 4 ' min [3:0] $end
$var wire 4 ( sec_ones [3:0] $end
$var wire 4 ) sec_tens [3:0] $end
$var reg 7 * min_segs [6:0] $end
$var reg 7 + sec_ones_segs [6:0] $end
$var reg 7 , sec_tens_segs [6:0] $end
$upscope $end
$upscope $end
$enddefinitions $end
$comment Show the parameter values. $end
$dumpall
$end
#0
$dumpvars
b1 ,
b1 +
b1 *
b0 )
b0 (
b0 '
b0 &
b0 %
b0 $
b1 #
b1 "
b1 !
$end
#5
b1001111 "
b1001111 +
b1001111 !
b1001111 ,
b1001111 #
b1001111 *
b1 %
b1 (
b1 &
b1 )
b1 $
b1 '
#10
b10010 "
b10010 +
b10010 !
b10010 ,
b10010 #
b10010 *
b10 %
b10 (
b10 &
b10 )
b10 $
b10 '
#15
b110 "
b110 +
b110 !
b110 ,
b110 #
b110 *
b11 %
b11 (
b11 &
b11 )
b11 $
b11 '
#20
b1001100 "
b1001100 +
b1001100 !
b1001100 ,
b1001100 #
b1001100 *
b100 %
b100 (
b100 &
b100 )
b100 $
b100 '
#25
b100100 "
b100100 +
b100100 !
b100100 ,
b100100 #
b100100 *
b101 %
b101 (
b101 &
b101 )
b101 $
b101 '
#30
b100000 "
b100000 +
b100000 !
b100000 ,
b100000 #
b100000 *
b110 %
b110 (
b110 &
b110 )
b110 $
b110 '
#35
b1101 "
b1101 +
b1101 !
b1101 ,
b1101 #
b1101 *
b111 %
b111 (
b111 &
b111 )
b111 $
b111 '
#40
b0 "
b0 +
b0 !
b0 ,
b0 #
b0 *
b1000 %
b1000 (
b1000 &
b1000 )
b1000 $
b1000 '
#45
b100 "
b100 +
b100 !
b100 ,
b100 #
b100 *
b1001 %
b1001 (
b1001 &
b1001 )
b1001 $
b1001 '
