TESTE - CONTADOR/contador_mod10.v
module contador_mod10 (data, clk, load, reset, count, tc, stop);
  
  input [3:0] data;
  input clk, load, reset, stop;
  output [3:0] count;
  output tc;
  
  wire reset_comb;
  reg [3:0] reg_count;
  wire tc;
  
  assign count = reg_count;
  assign reset_comb = (reset & ((reg_count == 4'b0000)? 1'b0 : 1'b1));
  assign tc = (reg_count == 4'b0000)? 1'b1 : 1'b0;
  
  always @ (posedge clk) begin
    
    if (load)
      reg_count <= data;
    else
      if (!stop)
        reg_count <= reg_count;
      else
        if (!reset_comb)
            reg_count <= 4'b1001;
        else
            reg_count <= reg_count - 1'b1;

  end
  
endmodule

microwave-main/Nivel1/Nivel2/counter/Nivel3/contador_mod6.v
module contador_mod6(data, clk, load, reset, count, tc, stop);
  
  input [3:0] data;
  input clk, load, reset, stop;
  output [3:0] count;
  output tc;
  
  wire reset_comb;
  reg [3:0] reg_count;
  wire tc;
  
  assign count = reg_count;
  assign reset_comb = (reset & ((reg_count == 3'b000)? 1'b0 : 1'b1));
  assign tc = (reg_count == 3'b000)? 1'b1 : 1'b0;
  
  always @ (posedge clk) begin
    
    if (load)
      reg_count <= data;
    else
	    if (!stop)
	      reg_count <= reg_count;
	    else
	      if (!reset_comb)
	       	reg_count <= 3'b101;
	      else
	      	reg_count <= reg_count - 1'b1;
  end
  always @(negedge clear) begin
        if (!clear) begin
            reg_count <= 4'b0000;
        end
  end
  
endmodule

TESTE - CONTADOR/contador_nivel2.v
`include "contador_mod10.v"
`include "contador_mod6.v"

`timescale 1ns/1ps

module contador_nivel2(uni_sec, dez_sec, min, clk, enable, load, count_us, count_ds, count_m, zero);

  input [3:0] uni_sec, dez_sec, min;
  input wire clk, enable, load;
  output wire [3:0] count_us, count_ds, count_m;
  output wire zero;
  
  wire tc1;
  wire tc2;
  wire tc4;
  
  contador_mod10 us(uni_sec, clk, load, enable, count_us, tc1, enable);
  contador_mod6 ds(dez_sec, clk, load, enable, count_ds, tc2, tc1);
  
  wire tc3 = tc2 & tc1;
  
  contador_mod10 ms(min, clk, load, enable, count_m, tc4, tc3);
  
  assign zero = tc1 & tc2 & tc4;
  
endmodule

bin/contador_nivel2_tb.v
`timescale 1ns/1ps
`include "contador_nivel2.v"

module contador_nivel2_teste();

 	reg [3:0] uni_sec, min;
    reg [3:0] dez_sec; 
  	reg clk, enable, load;
  	wire [3:0] count_us, count_m;
    wire [3:0] count_ds; 
  	wire zero;
    integer i;
  
  	contador_nivel2 dut(uni_sec, dez_sec, min, clk, enable, load, count_us, count_ds, count_m, zero);

	initial
		begin
		
			$dumpfile("contador_nivel2_teste.vcd");
			$dumpvars(0,contador_nivel2_teste);
          
           enable = 0; 
           uni_sec = 4'b0111;
           dez_sec = 3'b101;
           min = 4'b1000;
           load = 1; 
           #5 enable = 1;
           #5 load = 0; 
           #10;
        end
  
  initial
    
    begin
    	clk = 1'b0;
  	end
		
  initial
    begin
    	#5 clk = ~clk;
      for(i = 0; i < 26; i= i + 1)
        begin
          #5 clk = ~clk;
        end
      
    end
      
endmodule

microwave-main/Nivel1/Nivel2/counter/contador_nivel2_teste.vcd
$date
	Sat Apr 22 13:17:01 2023
$end
$version
	Icarus Verilog
$end
$timescale
	1ps
$end
$scope module contador_nivel2_teste $end
$var wire 1 ! zero $end
$var wire 4 " count_us [3:0] $end
$var wire 4 # count_m [3:0] $end
$var wire 4 $ count_ds [3:0] $end
$var reg 1 % clk $end
$var reg 4 & dez_sec [3:0] $end
$var reg 1 ' enable $end
$var reg 1 ( load $end
$var reg 4 ) min [3:0] $end
$var reg 4 * uni_sec [3:0] $end
$var integer 32 + i [31:0] $end
$scope module dut $end
$var wire 1 % clk $end
$var wire 4 , dez_sec [3:0] $end
$var wire 1 ' enable $end
$var wire 1 ( load $end
$var wire 4 - min [3:0] $end
$var wire 1 . tc3 $end
$var wire 4 / uni_sec [3:0] $end
$var wire 1 ! zero $end
$var wire 1 0 tc4 $end
$var wire 1 1 tc2 $end
$var wire 1 2 tc1 $end
$var wire 4 3 count_us [3:0] $end
$var wire 4 4 count_m [3:0] $end
$var wire 4 5 count_ds [3:0] $end
$scope module ds $end
$var wire 1 % clk $end
$var wire 4 6 count [3:0] $end
$var wire 4 7 data [3:0] $end
$var wire 1 ( load $end
$var wire 1 ' reset $end
$var wire 1 8 reset_comb $end
$var wire 1 1 tc $end
$var wire 1 2 stop $end
$var reg 4 9 reg_count [3:0] $end
$upscope $end
$scope module ms $end
$var wire 1 % clk $end
$var wire 4 : count [3:0] $end
$var wire 4 ; data [3:0] $end
$var wire 1 ( load $end
$var wire 1 ' reset $end
$var wire 1 < reset_comb $end
$var wire 1 . stop $end
$var wire 1 0 tc $end
$var reg 4 = reg_count [3:0] $end
$upscope $end
$scope module us $end
$var wire 1 % clk $end
$var wire 4 > count [3:0] $end
$var wire 4 ? data [3:0] $end
$var wire 1 ( load $end
$var wire 1 ' reset $end
$var wire 1 @ reset_comb $end
$var wire 1 ' stop $end
$var wire 1 2 tc $end
$var reg 4 A reg_count [3:0] $end
$upscope $end
$upscope $end
$upscope $end
$enddefinitions $end
$comment Show the parameter values. $end
$dumpall
$end
#0
$dumpvars
bx A
0@
b111 ?
bx >
bx =
0<
b1000 ;
bx :
bx 9
08
b101 7
bx 6
bx 5
bx 4
bx 3
x2
x1
x0
b111 /
x.
b1000 -
b101 ,
bx +
b111 *
b1000 )
1(
0'
b101 &
0%
bx $
bx #
bx "
x!
$end
#5000
0.
0!
02
01
00
b111 "
b111 3
b111 >
b111 A
b101 $
b101 5
b101 6
b101 9
b1000 #
b1000 4
b1000 :
b1000 =
18
1<
1@
b0 +
1%
1'
#10000
b1 +
0%
0(
#15000
b110 "
b110 3
b110 >
b110 A
b10 +
1%
#20000
b11 +
0%
#25000
b101 "
b101 3
b101 >
b101 A
b100 +
1%
#30000
b101 +
0%
#35000
b100 "
b100 3
b100 >
b100 A
b110 +
1%
#40000
b111 +
0%
#45000
b11 "
b11 3
b11 >
b11 A
b1000 +
1%
#50000
b1001 +
0%
#55000
b10 "
b10 3
b10 >
b10 A
b1010 +
1%
#60000
b1011 +
0%
#65000
b1 "
b1 3
b1 >
b1 A
b1100 +
1%
#70000
b1101 +
0%
#75000
0@
12
b0 "
b0 3
b0 >
b0 A
b1110 +
1%
#80000
b1111 +
0%
#85000
1@
02
b1001 "
b1001 3
b1001 >
b1001 A
b100 $
b100 5
b100 6
b100 9
b10000 +
1%
#90000
b10001 +
0%
#95000
b1000 "
b1000 3
b1000 >
b1000 A
b10010 +
1%
#100000
b10011 +
0%
#105000
b111 "
b111 3
b111 >
b111 A
b10100 +
1%
#110000
b10101 +
0%
#115000
b110 "
b110 3
b110 >
b110 A
b10110 +
1%
#120000
b10111 +
0%
#125000
b101 "
b101 3
b101 >
b101 A
b11000 +
1%
#130000
b11001 +
0%
#135000
b100 "
b100 3
b100 >
b100 A
b11010 +
1%
